README.md
setup.cfg
setup.py
haburas/__init__.py
haburas/admin.py
haburas/apps.py
haburas/models.py
haburas/tests.py
haburas/urls.py
haburas/views.py
haburas.egg-info/PKG-INFO
haburas.egg-info/SOURCES.txt
haburas.egg-info/dependency_links.txt
haburas.egg-info/requires.txt
haburas.egg-info/top_level.txt