Metadata-Version: 1.1
Name: haburas
Version: 0.1.0
Summary: make app for hadezta
Home-page: https://github.com/eraulo/Setup_haburas/
Author: Mariano de Deus
Author-email: dedeus_mariano@yahoo.com
License: MIT
Platform: UNKNOWN
Classifier: Development Status :: 4 - Beta
Classifier: Environment :: Web Environment
Classifier: Framework :: Django
Classifier: Intended Audience :: Developers
Classifier: Operating System :: OS Independent
Classifier: Programming Language :: Python
Classifier: Programming Language :: Python :: 3
Classifier: Topic :: Internet :: WWW/HTTP
Classifier: Topic :: Internet :: WWW/HTTP :: Dynamic Content
